{
  "name": "MERN Stack",
  // "build": { "dockerfile": "Dockerfile" },
  "dockerComposeFile": "docker-compose.yml",
  "service": "nodejs",
  "workspaceFolder": "/workspace",

  "customizations": {
    "vscode": {
      "extensions": [
        "esbenp.prettier-vscode",
        "mongodb.mongodb-vscode",
        "sdras.night-owl",
        "dsznajder.es7-react-js-snippets",
        "ritwickdey.LiveServer",
        "Postman.postman-for-vscode",
        "google.geminicodeassist"
      ]
    }
  },

  // "forwardPorts": [5001]
}
